crashlens_logger/__init__.py
crashlens_logger/logger.py
crashlens_logger-1.0.6.dist-info/entry_points.txt
crashlens_logger-1.0.6.dist-info/METADATA
crashlens_logger-1.0.6.dist-info/WHEEL
crashlens_logger-1.0.6.dist-info/RECORD
