Metadata-Version: 2.1
Name: crashlens-logger
Version: 1.0.6
Summary: CLI tool to generate structured LLM logs for CrashLens cost detection
Keywords: llm,logging,finops,cost-tracking,token-usage
Author: Aditya Singh
Requires-Python: >=3.9,<4.0
Classifier: Development Status :: 3 - Alpha
Classifier: Intended Audience :: Developers
Classifier: License :: OSI Approved :: MIT License
Classifier: Operating System :: OS Independent
Classifier: Programming Language :: Python :: 3
Classifier: Programming Language :: Python :: 3.9
Classifier: Programming Language :: Python :: 3.10
Classifier: Programming Language :: Python :: 3.11
Classifier: Programming Language :: Python :: 3.12
Classifier: Topic :: Software Development :: Libraries :: Python Modules
Classifier: Topic :: System :: Logging
Classifier: Topic :: System :: Monitoring
Requires-Dist: click (>=8.0,<9.0)
Requires-Dist: orjson (>=3.9.0,<4.0.0)
Requires-Dist: pyyaml (>=6.0,<7.0)
Requires-Dist: rich (>=13.0.0,<14.0.0)
